[
    {
        "id": 1780759619,
        "name": "STAR SPORTS",
        "image": "https:\/\/i.top4top.io\/p_3809baapp1.jpg",
        "sort_order": 0
    },
    {
        "id": 1780761966,
        "name": "World Cup | كأس العالم",
        "image": "https:\/\/j.top4top.io\/p_3795lv1ga0.jpg",
        "sort_order": 1
    },
    {
        "id": 1780087414,
        "name": "BEIN SPORTS",
        "image": "https:\/\/k.top4top.io\/p_3715q5plw1.jpg",
        "sort_order": 2
    },
    {
        "id": 1780745923,
        "name": "THMANYA SPORTS",
        "image": "https:\/\/i.ibb.co\/dTbX08F\/image.png",
        "sort_order": 5
    },
    {
        "id": 1780761200,
        "name": "ALWAN SPORTS",
        "image": "https:\/\/i.ibb.co\/wNCKNMMH\/alwan-sports.png",
        "sort_order": 4
    },
    {
        "id": 1780762225,
        "name": "STARZ PLAY",
        "image": "https:\/\/e.top4top.io\/p_35783xyyz0.jpg",
        "sort_order": 6
    },
    {
        "id": 1780762505,
        "name": "SHAHID SPORTS",
        "image": "https:\/\/e.top4top.io\/p_3581ohanr0.png",
        "sort_order": 7
    }
]